vd_DongGoi/__init__.py
vd_DongGoi/app.py
ViduDongGoiPython-1.0.0.dist-info/LICENSE
ViduDongGoiPython-1.0.0.dist-info/METADATA
ViduDongGoiPython-1.0.0.dist-info/WHEEL
ViduDongGoiPython-1.0.0.dist-info/top_level.txt
ViduDongGoiPython-1.0.0.dist-info/RECORD
