Metadata-Version: 2.1
Name: ViduDongGoiPython
Version: 1.0.0
Summary: Python for Math
Home-page: https://github.com/pypa/sampleproject
Author: TranNgocTin
Author-email: tnt123@gmail.com
Classifier: Programming Language :: Python :: 2
Classifier: License :: OSI Approved :: MIT License
Classifier: Operating System :: OS Independent
License-File: LICENSE
